Metadata-Version: 2.1
Name: codecanvas
Version: 1.1.0
Summary: CodeCanvas é um pacote Python que permite adicionar estilos ao console.
Author: Jean Branco
Author-email: jeanlourencobranco13@gmail.com
License: MIT License
Keywords: code canvas
License-File: LICENCE
